aiden_server/__init__.py
aiden_server/server.py
aiden_server-0.1.3.dist-info/METADATA
aiden_server-0.1.3.dist-info/WHEEL
aiden_server-0.1.3.dist-info/entry_points.txt
aiden_server-0.1.3.dist-info/RECORD
