Metadata-Version: 2.4
Name: aiden-server
Version: 0.1.3
Summary: Add your description here
Requires-Python: >=3.10
Requires-Dist: mcp[cli]>=1.9.3
